[{"station_id": 31510, "year": 1915, "monthly_data": {"January": 172.0, "February": 169.0, "March": 172.0, "April": 155.0, "May": 214.0, "June": 245.0, "July": 225.0, "August": 195.0, "September": 176.0, "October": 190.0, "November": 160.0, "December": 118.0}, "wmo_id": 31517}, {"station_id": 31510, "year": 1916, "monthly_data": {"January": 155.0, "February": 194.0, "March": 230.0, "April": 218.0, "May": 230.0, "June": 185.0, "July": 247.0, "August": 290.0, "September": 194.0, "October": 191.0, "November": 126.0, "December": 111.0}, "wmo_id": 31517}, {"station_id": 31510, "year": 1917, "monthly_data": {"January": 141.0, "February": 188.0, "March": 246.0, "April": 167.0, "May": 218.0, "June": 199.0, "July": 229.0, "August": 247.0, "September": 231.0, "October": 156.0, "November": 139.0, "December": 109.0}, "wmo_id": 31517}, {"station_id": 31510, "year": 1918, "monthly_data": {"January": 144.0, "February": 199.0, "March": 251.0, "April": 178.0, "May": 249.0, "June": 218.0, "July": 284.0, "August": 242.0, "September": 169.0, "October": 201.0, "November": 140.0, "December": 149.0}, "wmo_id": 31517}, {"station_id": 31510, "year": 1919, "monthly_data": {"January": 155.0, "February": 163.0, "March": 218.0, "April": 170.0, "May": 257.0, "June": 270.0, "July": 319.0, "August": 233.0, "September": 217.0, "October": 140.0, "November": 142.0, "December": 116.0}, "wmo_id": 31517}, {"station_id": 31510, "year": 1920, "monthly_data": {"January": 116.0, "February": 173.0, "March": 222.0, "April": 219.0, "May": 272.0, "June": 186.0, "July": 258.0, "August": 239.0, "September": 151.0, "October": 184.0, "November": 150.0, "December": 106.0}, "wmo_id": 31517}, {"station_id": 31510, "year": 1921, "monthly_data": {"January": 136.0, "February": 183.0, "March": 248.0, "April": 192.0, "May": 249.0, "June": 248.0, "July": 306.0, "August": 218.0, "September": 179.0, "October": 123.0, "November": 158.0, "December": 149.0}, "wmo_id": 31517}, {"station_id": 31510, "year": 1922, "monthly_data": {"January": 160.0, "February": 153.0, "March": 199.0, "April": 221.0, "May": 144.0, "June": 276.0, "July": 206.0, "August": 241.0, "September": 140.0, "October": 162.0, "November": 164.0, "December": 149.0}, "wmo_id": 31517}, {"station_id": 31510, "year": 1923, "monthly_data": {"January": 177.0, "February": 148.0, "March": 214.0, "April": 248.0, "May": 185.0, "June": 173.0, "July": 248.0, "August": 216.0, "September": 180.0, "October": 141.0, "November": 166.0, "December": 117.0}, "wmo_id": 31517}, {"station_id": 31510, "year": 1924, "monthly_data": {"January": 123.0, "February": 175.0, "March": 214.0, "April": 201.0, "May": 251.0, "June": null, "July": 221.0, "August": 226.0, "September": 196.0, "October": 177.0, "November": 167.0, "December": 117.0}, "wmo_id": 31517}, {"station_id": 31510, "year": 1925, "monthly_data": {"January": 142.0, "February": 207.0, "March": 250.0, "April": 203.0, "May": 227.0, "June": 256.0, "July": 313.0, "August": 198.0, "September": 170.0, "October": 200.0, "November": 138.0, "December": 107.0}, "wmo_id": 31517}, {"station_id": 31510, "year": 1926, "monthly_data": {"January": 150.0, "February": 173.0, "March": 229.0, "April": 189.0, "May": 210.0, "June": 232.0, "July": 258.0, "August": 251.0, "September": 179.0, "October": 157.0, "November": 158.0, "December": 143.0}, "wmo_id": 31517}, {"station_id": 31510, "year": 1927, "monthly_data": {"January": 189.0, "February": 205.0, "March": 214.0, "April": 194.0, "May": 224.0, "June": 229.0, "July": 277.0, "August": 251.0, "September": 233.0, "October": 156.0, "November": 147.0, "December": 156.0}, "wmo_id": 31517}, {"station_id": 31510, "year": 1928, "monthly_data": {"January": 156.0, "February": 220.0, "March": 198.0, "April": 238.0, "May": 238.0, "June": 262.0, "July": 216.0, "August": 193.0, "September": 138.0, "October": 193.0, "November": 139.0, "December": 174.0}, "wmo_id": 31517}, {"station_id": 31510, "year": 1929, "monthly_data": {"January": 181.0, "February": 210.0, "March": 234.0, "April": 196.0, "May": 261.0, "June": 204.0, "July": 243.0, "August": 211.0, "September": 172.0, "October": 161.0, "November": 165.0, "December": 128.0}, "wmo_id": 31517}, {"station_id": 31510, "year": 1930, "monthly_data": {"January": 181.0, "February": 166.0, "March": 241.0, "April": 220.0, "May": 244.0, "June": 263.0, "July": 276.0, "August": 179.0, "September": 178.0, "October": 228.0, "November": 96.0, "December": 161.0}, "wmo_id": 31517}, {"station_id": 31510, "year": 1931, "monthly_data": {"January": 146.0, "February": 213.0, "March": 196.0, "April": 218.0, "May": 177.0, "June": 199.0, "July": 292.0, "August": 271.0, "September": 128.0, "October": 176.0, "November": 155.0, "December": 154.0}, "wmo_id": 31517}, {"station_id": 31510, "year": 1932, "monthly_data": {"January": 140.0, "February": 213.0, "March": 188.0, "April": 200.0, "May": 190.0, "June": 171.0, "July": null, "August": 132.0, "September": 217.0, "October": 180.0, "November": 125.0, "December": 142.0}, "wmo_id": 31517}, {"station_id": 31510, "year": 1933, "monthly_data": {"January": 188.0, "February": 182.0, "March": 239.0, "April": 232.0, "May": 224.0, "June": 261.0, "July": 312.0, "August": 246.0, "September": 171.0, "October": 206.0, "November": 192.0, "December": 150.0}, "wmo_id": 31517}, {"station_id": 31510, "year": 1934, "monthly_data": {"January": 193.0, "February": 234.0, "March": 216.0, "April": 247.0, "May": 154.0, "June": 258.0, "July": 212.0, "August": 204.0, "September": 184.0, "October": 165.0, "November": 152.0, "December": 161.0}, "wmo_id": 31517}, {"station_id": 31510, "year": 1935, "monthly_data": {"January": 192.0, "February": 206.0, "March": 218.0, "April": 174.0, "May": 222.0, "June": 279.0, "July": 273.0, "August": 208.0, "September": 180.0, "October": 116.0, "November": 142.0, "December": 140.0}, "wmo_id": 31517}, {"station_id": 31510, "year": 1936, "monthly_data": {"January": 119.0, "February": 173.0, "March": 245.0, "April": 230.0, "May": 218.0, "June": 265.0, "July": 209.0, "August": 248.0, "September": 177.0, "October": 163.0, "November": 142.0, "December": 116.0}, "wmo_id": 31517}, {"station_id": 31510, "year": 1937, "monthly_data": {"January": 174.0, "February": 189.0, "March": 236.0, "April": 211.0, "May": 191.0, "June": 291.0, "July": 193.0, "August": 250.0, "September": 190.0, "October": 148.0, "November": 155.0, "December": 119.0}, "wmo_id": 31517}, {"station_id": 31510, "year": 1938, "monthly_data": {"January": 154.0, "February": 174.0, "March": 244.0, "April": 181.0, "May": 195.0, "June": 184.0, "July": 168.0, "August": 187.0, "September": 131.0, "October": 135.0, "November": 118.0, "December": 121.0}, "wmo_id": 31517}, {"station_id": 31510, "year": 1939, "monthly_data": {"January": 149.0, "February": 209.0, "March": 145.0, "April": 257.0, "May": null, "June": null, "July": null, "August": 221.0, "September": 176.0, "October": 163.0, "November": null, "December": 132.0}, "wmo_id": 31517}, {"station_id": 31510, "year": 1940, "monthly_data": {"January": 116.0, "February": 183.0, "March": 190.0, "April": 152.0, "May": 189.0, "June": 239.0, "July": 201.0, "August": 283.0, "September": 184.0, "October": 159.0, "November": 131.0, "December": 87.0}, "wmo_id": 31517}, {"station_id": 31510, "year": 1941, "monthly_data": {"January": 126.0, "February": 153.0, "March": 200.0, "April": 180.0, "May": 194.0, "June": 276.0, "July": 211.0, "August": 217.0, "September": 176.0, "October": 175.0, "November": 132.0, "December": 113.0}, "wmo_id": 31517}, {"station_id": 31510, "year": 1942, "monthly_data": {"January": null, "February": null, "March": 188.0, "April": 142.0, "May": 126.0, "June": 225.0, "July": 153.0, "August": 235.0, "September": 166.0, "October": 155.0, "November": 129.0, "December": 167.0}, "wmo_id": 31517}, {"station_id": 31510, "year": 1943, "monthly_data": {"January": 142.0, "February": 167.0, "March": 207.0, "April": 212.0, "May": 208.0, "June": 169.0, "July": 229.0, "August": 203.0, "September": 168.0, "October": 176.0, "November": 144.0, "December": null}, "wmo_id": 31517}, {"station_id": 31510, "year": 1944, "monthly_data": {"January": null, "February": null, "March": null, "April": null, "May": null, "June": null, "July": 281.0, "August": null, "September": 183.0, "October": 157.0, "November": 114.0, "December": 150.0}, "wmo_id": 31517}, {"station_id": 31510, "year": 1945, "monthly_data": {"January": 157.0, "February": 152.0, "March": 189.0, "April": 187.0, "May": 226.0, "June": 173.0, "July": 216.0, "August": 139.0, "September": 205.0, "October": 167.0, "November": 129.0, "December": 117.0}, "wmo_id": 31517}, {"station_id": 31510, "year": 1946, "monthly_data": {"January": 128.0, "February": 155.0, "March": 195.0, "April": 178.0, "May": 219.0, "June": null, "July": null, "August": null, "September": 137.0, "October": 164.0, "November": 144.0, "December": 119.0}, "wmo_id": 31517}, {"station_id": 31510, "year": 1947, "monthly_data": {"January": 142.0, "February": 189.0, "March": 209.0, "April": 187.0, "May": 220.0, "June": 249.0, "July": 147.0, "August": 165.0, "September": 182.0, "October": 155.0, "November": 169.0, "December": 167.0}, "wmo_id": 31517}, {"station_id": 31510, "year": 1948, "monthly_data": {"January": 180.0, "February": 210.0, "March": 232.0, "April": 191.0, "May": 220.0, "June": 178.0, "July": 250.0, "August": 205.0, "September": 176.0, "October": 170.0, "November": 199.0, "December": 146.0}, "wmo_id": 31517}, {"station_id": 31510, "year": 1951, "monthly_data": {"January": 124.0, "February": 196.0, "March": 218.0, "April": 149.0, "May": 251.0, "June": 260.0, "July": 185.0, "August": 161.0, "September": 147.0, "October": 188.0, "November": 185.0, "December": 153.0}, "wmo_id": 31517}, {"station_id": 31510, "year": 1952, "monthly_data": {"January": 178.0, "February": 229.0, "March": 268.0, "April": 176.0, "May": 181.0, "June": 211.0, "July": 209.0, "August": 253.0, "September": 147.0, "October": 188.0, "November": 105.0, "December": 84.0}, "wmo_id": 31517}, {"station_id": 31510, "year": 1953, "monthly_data": {"January": 125.0, "February": 209.0, "March": 243.0, "April": null, "May": 148.0, "June": 188.0, "July": 183.0, "August": 197.0, "September": 178.0, "October": 189.0, "November": 165.0, "December": 99.0}, "wmo_id": 31517}, {"station_id": 31510, "year": 1954, "monthly_data": {"January": 157.0, "February": 164.0, "March": 233.0, "April": 210.0, "May": 214.0, "June": 188.0, "July": 197.0, "August": 263.0, "September": 183.0, "October": 114.0, "November": 151.0, "December": 137.0}, "wmo_id": 31517}, {"station_id": 31510, "year": 1955, "monthly_data": {"January": 139.0, "February": 182.0, "March": 197.0, "April": 241.0, "May": 213.0, "June": 208.0, "July": 272.0, "August": 246.0, "September": 140.0, "October": 191.0, "November": 184.0, "December": 97.0}, "wmo_id": 31517}, {"station_id": 31510, "year": 1956, "monthly_data": {"January": 126.0, "February": 177.0, "March": 203.0, "April": 194.0, "May": 200.0, "June": 185.0, "July": 167.0, "August": 273.0, "September": 108.0, "October": 139.0, "November": 121.0, "December": 109.0}, "wmo_id": 31517}, {"station_id": 31510, "year": 1957, "monthly_data": {"January": 134.0, "February": 166.0, "March": 216.0, "April": 178.0, "May": 240.0, "June": 284.0, "July": 179.0, "August": 158.0, "September": 147.0, "October": 186.0, "November": 129.0, "December": 133.0}, "wmo_id": 31517}, {"station_id": 31510, "year": 1958, "monthly_data": {"January": 135.0, "February": 196.0, "March": 199.0, "April": 148.0, "May": 229.0, "June": 250.0, "July": 228.0, "August": 225.0, "September": 175.0, "October": 178.0, "November": 183.0, "December": 120.0}, "wmo_id": 31517}, {"station_id": 31510, "year": 1959, "monthly_data": {"January": 145.0, "February": 178.0, "March": 196.0, "April": 160.0, "May": 202.0, "June": 238.0, "July": 188.0, "August": 163.0, "September": 146.0, "October": 105.0, "November": 159.0, "December": 128.0}, "wmo_id": 31517}, {"station_id": 31510, "year": 1960, "monthly_data": {"January": 152.0, "February": 164.0, "March": 167.0, "April": 188.0, "May": 224.0, "June": 180.0, "July": 290.0, "August": 176.0, "September": 143.0, "October": 209.0, "November": 102.0, "December": 112.0}, "wmo_id": 31517}, {"station_id": 31510, "year": 1961, "monthly_data": {"January": 127.0, "February": 162.0, "March": 213.0, "April": 217.0, "May": 197.0, "June": 208.0, "July": 206.0, "August": 187.0, "September": 169.0, "October": 219.0, "November": 140.0, "December": 107.0}, "wmo_id": 31517}, {"station_id": 31510, "year": 1962, "monthly_data": {"January": null, "February": 219.0, "March": 224.0, "April": 232.0, "May": 223.0, "June": 277.0, "July": 174.0, "August": 192.0, "September": 174.0, "October": 207.0, "November": 171.0, "December": 118.0}, "wmo_id": 31517}, {"station_id": 31510, "year": 1963, "monthly_data": {"January": null, "February": 197.0, "March": 208.0, "April": 160.0, "May": 248.0, "June": 223.0, "July": 225.0, "August": 234.0, "September": 134.0, "October": 182.0, "November": 173.0, "December": 136.0}, "wmo_id": 31517}, {"station_id": 31510, "year": 1964, "monthly_data": {"January": null, "February": null, "March": 228.0, "April": 211.0, "May": 300.0, "June": 218.0, "July": 287.0, "August": 283.0, "September": 200.0, "October": 159.0, "November": 144.0, "December": 121.0}, "wmo_id": 31517}, {"station_id": 31510, "year": 1965, "monthly_data": {"January": null, "February": 219.0, "March": 239.0, "April": 263.0, "May": 268.0, "June": 322.0, "July": 236.0, "August": 241.0, "September": 164.0, "October": 183.0, "November": null, "December": 132.0}, "wmo_id": 31517}, {"station_id": 31510, "year": 1966, "monthly_data": {"January": 147.0, "February": 174.0, "March": 252.0, "April": 250.0, "May": 276.0, "June": 281.0, "July": null, "August": null, "September": null, "October": null, "November": null, "December": null}, "wmo_id": 31517}]