[{"station_id": 28666, "year": 1966, "monthly_data": {"January": 1.0, "February": 5.01, "March": 6.06, "April": 5.28, "May": 5.21, "June": 6.03, "July": 5.95, "August": 4.53, "September": 5.28, "October": 4.63, "November": 7.68, "December": 7.76}, "wmo_id": 28668}, {"station_id": 28666, "year": 1966, "monthly_data": {"January": 2.0, "February": 2.2, "March": 3.55, "April": 2.07, "May": 3.63, "June": 4.57, "July": 3.99, "August": 2.73, "September": 3.25, "October": 2.96, "November": 5.26, "December": 5.91}, "wmo_id": 28668}, {"station_id": 28666, "year": 1967, "monthly_data": {"January": 1.0, "February": 5.01, "March": 2.42, "April": 5.46, "May": 2.82, "June": 6.31, "July": 5.3, "August": 6.02, "September": 4.65, "October": 5.97, "November": 6.04, "December": 5.8}, "wmo_id": 28668}, {"station_id": 28666, "year": 1967, "monthly_data": {"January": 2.0, "February": 2.19, "March": 0.45, "April": 3.19, "May": 0.91, "June": 4.06, "July": 3.25, "August": 3.75, "September": 3.34, "October": 4.37, "November": 4.45, "December": 3.96}, "wmo_id": 28668}, {"station_id": 28666, "year": 1968, "monthly_data": {"January": 1.0, "February": 5.77, "March": 4.41, "April": 5.16, "May": 5.69, "June": 4.74, "July": 6.01, "August": 7.19, "September": 4.84, "October": 6.21, "November": 4.93, "December": 6.63}, "wmo_id": 28668}, {"station_id": 28666, "year": 1968, "monthly_data": {"January": 2.0, "February": 1.74, "March": 1.53, "April": 3.63, "May": 3.84, "June": 2.92, "July": 4.0, "August": 4.6, "September": 2.27, "October": 3.7, "November": 2.74, "December": 3.42}, "wmo_id": 28668}, {"station_id": 28666, "year": 1969, "monthly_data": {"January": 1.0, "February": 3.28, "March": 4.69, "April": 3.29, "May": 5.7, "June": 6.85, "July": 5.8, "August": 6.6, "September": 6.83, "October": 5.1, "November": 8.66, "December": 6.87}, "wmo_id": 28668}, {"station_id": 28666, "year": 1969, "monthly_data": {"January": 2.0, "February": 0.36, "March": 1.56, "April": 0.66, "May": 2.23, "June": 4.85, "July": 3.56, "August": 4.28, "September": 4.58, "October": 2.88, "November": 7.42, "December": 4.12}, "wmo_id": 28668}, {"station_id": 28666, "year": 1970, "monthly_data": {"January": 1.0, "February": 5.29, "March": 3.74, "April": 5.21, "May": 5.6, "June": 5.92, "July": 5.91, "August": 5.75, "September": 6.57, "October": 4.6, "November": 7.75, "December": 6.23}, "wmo_id": 28668}, {"station_id": 28666, "year": 1970, "monthly_data": {"January": 2.0, "February": 1.32, "March": 0.83, "April": 2.6, "May": 3.55, "June": 4.33, "July": 4.35, "August": 4.19, "September": 4.67, "October": 2.12, "November": 6.11, "December": 3.57}, "wmo_id": 28668}, {"station_id": 28666, "year": 1971, "monthly_data": {"January": 1.0, "February": 6.61, "March": 4.05, "April": 4.26, "May": 5.88, "June": 6.38, "July": 5.47, "August": 5.37, "September": 5.59, "October": 3.95, "November": 7.35, "December": 7.23}, "wmo_id": 28668}, {"station_id": 28666, "year": 1971, "monthly_data": {"January": 2.0, "February": 3.69, "March": 1.0, "April": 1.75, "May": 2.07, "June": 4.82, "July": 3.51, "August": 3.25, "September": 4.15, "October": 1.94, "November": 4.76, "December": 6.11}, "wmo_id": 28668}, {"station_id": 28666, "year": 1972, "monthly_data": {"January": 1.0, "February": 4.16, "March": 4.85, "April": 5.57, "May": 7.8, "June": 4.55, "July": 6.21, "August": 4.58, "September": 4.38, "October": 7.12, "November": 6.12, "December": 6.84}, "wmo_id": 28668}, {"station_id": 28666, "year": 1972, "monthly_data": {"January": 2.0, "February": 0.79, "March": 1.17, "April": 2.57, "May": 4.98, "June": 2.91, "July": 4.3, "August": 3.04, "September": 2.67, "October": 4.49, "November": 2.73, "December": 3.19}, "wmo_id": 28668}, {"station_id": 28666, "year": 1973, "monthly_data": {"January": 1.0, "February": 4.76, "March": 5.55, "April": 5.05, "May": 1.81, "June": 3.5, "July": 5.47, "August": 6.27, "September": 4.07, "October": 7.22, "November": 6.2, "December": 6.79}, "wmo_id": 28668}, {"station_id": 28666, "year": 1973, "monthly_data": {"January": 2.0, "February": 0.34, "March": 2.22, "April": 1.96, "May": 0.66, "June": 2.05, "July": 3.29, "August": 4.04, "September": 2.39, "October": 4.33, "November": 2.42, "December": 2.59}, "wmo_id": 28668}, {"station_id": 28666, "year": 1974, "monthly_data": {"January": 1.0, "February": 3.8, "March": 4.74, "April": 6.61, "May": 5.49, "June": 4.62, "July": 5.56, "August": 3.81, "September": 4.95, "October": 4.54, "November": 4.86, "December": 5.73}, "wmo_id": 28668}, {"station_id": 28666, "year": 1974, "monthly_data": {"January": 2.0, "February": 1.12, "March": 1.39, "April": 2.62, "May": 2.38, "June": 1.72, "July": 3.28, "August": 1.54, "September": 3.14, "October": 1.71, "November": 0.88, "December": 2.75}, "wmo_id": 28668}, {"station_id": 28666, "year": 1975, "monthly_data": {"January": 1.0, "February": 6.4, "March": 5.65, "April": 5.6, "May": 6.1, "June": 4.26, "July": 4.71, "August": 4.35, "September": 4.31, "October": 4.89, "November": 6.22, "December": 6.06}, "wmo_id": 28668}, {"station_id": 28666, "year": 1975, "monthly_data": {"January": 2.0, "February": 1.71, "March": 0.95, "April": 1.48, "May": 2.91, "June": 2.12, "July": 2.07, "August": 2.95, "September": 3.11, "October": 2.85, "November": 4.23, "December": 3.59}, "wmo_id": 28668}, {"station_id": 28666, "year": 1976, "monthly_data": {"January": 1.0, "February": 6.41, "March": 4.16, "April": 2.65, "May": 3.8, "June": 5.04, "July": 5.22, "August": 5.76, "September": 4.38, "October": 4.46, "November": 6.4, "December": 6.65}, "wmo_id": 28668}, {"station_id": 28666, "year": 1976, "monthly_data": {"January": 2.0, "February": 2.91, "March": 1.1, "April": 1.11, "May": 1.48, "June": 2.54, "July": 3.45, "August": 4.46, "September": 1.95, "October": 2.57, "November": 4.39, "December": 2.34}, "wmo_id": 28668}, {"station_id": 28666, "year": 1978, "monthly_data": {"January": 1.0, "February": 4.85, "March": 5.1, "April": 5.45, "May": 4.78, "June": 4.81, "July": 4.88, "August": 6.59, "September": 6.09, "October": 5.25, "November": 6.11, "December": 6.72}, "wmo_id": 28668}, {"station_id": 28666, "year": 1978, "monthly_data": {"January": 2.0, "February": 0.86, "March": 0.53, "April": 1.4, "May": 2.72, "June": 1.97, "July": 2.4, "August": 4.26, "September": 3.21, "October": 2.21, "November": 3.46, "December": 3.13}, "wmo_id": 28668}, {"station_id": 28666, "year": 1979, "monthly_data": {"January": 1.0, "February": 4.3, "March": 6.15, "April": 5.01, "May": 3.91, "June": 4.7, "July": 6.34, "August": 4.69, "September": 4.99, "October": 6.37, "November": 6.7, "December": 6.59}, "wmo_id": 28668}, {"station_id": 28666, "year": 1979, "monthly_data": {"January": 2.0, "February": 0.49, "March": 1.42, "April": 0.78, "May": 1.08, "June": 2.63, "July": 3.78, "August": 2.12, "September": 2.51, "October": 2.82, "November": 2.67, "December": 1.58}, "wmo_id": 28668}, {"station_id": 28666, "year": 1980, "monthly_data": {"January": 1.0, "February": 5.0, "March": 3.2, "April": 3.01, "May": 4.45, "June": 4.46, "July": 6.19, "August": 5.2, "September": 5.56, "October": 5.77, "November": 5.66, "December": 5.04}, "wmo_id": 28668}, {"station_id": 28666, "year": 1980, "monthly_data": {"January": 2.0, "February": 0.51, "March": 0.03, "April": 0.67, "May": 1.23, "June": 1.12, "July": 3.69, "August": 2.57, "September": 2.94, "October": 2.79, "November": 1.7, "December": 1.78}, "wmo_id": 28668}, {"station_id": 28666, "year": 1981, "monthly_data": {"January": 1.0, "February": 6.02, "March": 5.35, "April": 6.03, "May": 6.03, "June": 4.8, "July": 4.72, "August": 4.17, "September": 2.73, "October": 5.88, "November": 4.59, "December": 6.85}, "wmo_id": 28668}, {"station_id": 28666, "year": 1981, "monthly_data": {"January": 2.0, "February": 2.19, "March": 1.97, "April": 1.93, "May": 2.58, "June": 2.36, "July": 1.62, "August": 2.04, "September": 1.16, "October": 2.64, "November": 2.8, "December": 4.61}, "wmo_id": 28668}, {"station_id": 28666, "year": 1982, "monthly_data": {"January": 1.0, "February": 6.0, "March": 5.8, "April": 5.39, "May": 5.52, "June": 4.76, "July": 5.01, "August": 4.41, "September": 4.54, "October": 4.24, "November": 7.96, "December": 7.76}, "wmo_id": 28668}, {"station_id": 28666, "year": 1982, "monthly_data": {"January": 2.0, "February": 1.86, "March": 1.2, "April": 1.02, "May": 1.97, "June": 2.27, "July": 2.31, "August": 2.22, "September": 2.23, "October": 1.86, "November": 6.33, "December": 6.37}, "wmo_id": 28668}, {"station_id": 28666, "year": 1983, "monthly_data": {"January": 1.0, "February": 6.93, "March": 6.64, "April": 5.72, "May": 5.83, "June": 5.64, "July": 5.8, "August": 4.52, "September": 5.74, "October": 7.27, "November": 6.87, "December": 6.56}, "wmo_id": 28668}, {"station_id": 28666, "year": 1983, "monthly_data": {"January": 2.0, "February": 4.33, "March": 3.09, "April": 2.49, "May": 2.24, "June": 3.91, "July": 3.16, "August": 2.45, "September": 3.77, "October": 5.83, "November": 4.52, "December": 4.14}, "wmo_id": 28668}, {"station_id": 28666, "year": 1984, "monthly_data": {"January": 1.0, "February": 5.93, "March": 3.93, "April": 5.44, "May": 5.64, "June": 5.69, "July": 4.89, "August": 4.61, "September": 5.35, "October": 6.88, "November": 8.58, "December": 6.48}, "wmo_id": 28668}, {"station_id": 28666, "year": 1984, "monthly_data": {"January": 2.0, "February": 3.78, "March": 0.95, "April": 3.12, "May": 2.45, "June": 2.85, "July": 3.25, "August": 2.67, "September": 3.6, "October": 5.38, "November": 7.07, "December": 3.23}, "wmo_id": 28668}, {"station_id": 28666, "year": 1985, "monthly_data": {"January": 1.0, "February": 5.88, "March": 5.69, "April": 4.09, "May": 5.9, "June": 5.63, "July": 5.2, "August": 5.95, "September": 5.02, "October": 4.46, "November": 7.03, "December": 7.11}, "wmo_id": 28668}, {"station_id": 28666, "year": 1985, "monthly_data": {"January": 2.0, "February": 1.09, "March": 0.78, "April": 1.62, "May": 3.59, "June": 3.92, "July": 2.72, "August": 4.36, "September": 3.37, "October": 2.21, "November": 5.57, "December": 4.44}, "wmo_id": 28668}, {"station_id": 28666, "year": 1986, "monthly_data": {"January": 1.0, "February": 6.66, "March": 5.21, "April": 5.48, "May": 4.1, "June": 6.38, "July": 6.05, "August": 6.59, "September": 6.72, "October": 5.69, "November": 6.38, "December": 6.75}, "wmo_id": 28668}, {"station_id": 28666, "year": 1986, "monthly_data": {"January": 2.0, "February": 2.77, "March": 1.42, "April": 1.94, "May": 1.55, "June": 4.86, "July": 3.36, "August": 4.78, "September": 4.67, "October": 2.85, "November": 3.64, "December": 4.55}, "wmo_id": 28668}, {"station_id": 28666, "year": 1987, "monthly_data": {"January": 1.0, "February": 6.71, "March": 7.18, "April": 2.59, "May": 5.83, "June": 6.07, "July": 4.27, "August": 5.48, "September": 6.42, "October": 7.98, "November": 6.11, "December": 4.21}, "wmo_id": 28668}, {"station_id": 28666, "year": 1987, "monthly_data": {"January": 2.0, "February": 2.93, "March": 1.65, "April": 0.37, "May": 2.86, "June": 3.1, "July": 1.7, "August": 2.11, "September": 4.25, "October": 5.49, "November": 4.24, "December": 2.48}, "wmo_id": 28668}, {"station_id": 28666, "year": 1988, "monthly_data": {"January": 1.0, "February": 5.96, "March": 3.39, "April": 2.98, "May": 5.38, "June": 5.56, "July": 5.14, "August": 5.53, "September": 4.96, "October": 5.97, "November": 5.96, "December": 6.81}, "wmo_id": 28668}, {"station_id": 28666, "year": 1988, "monthly_data": {"January": 2.0, "February": 1.77, "March": 0.17, "April": 0.96, "May": 1.99, "June": 3.2, "July": 2.62, "August": 3.24, "September": 3.15, "October": 3.99, "November": 3.9, "December": 3.26}, "wmo_id": 28668}, {"station_id": 28666, "year": 1989, "monthly_data": {"January": 1.0, "February": 7.02, "March": 4.77, "April": 4.59, "May": 6.69, "June": 5.99, "July": 4.25, "August": 3.8, "September": 6.53, "October": 5.69, "November": 6.58, "December": 6.54}, "wmo_id": 28668}, {"station_id": 28666, "year": 1989, "monthly_data": {"January": 2.0, "February": 3.0, "March": 2.3, "April": 1.52, "May": 3.36, "June": 4.43, "July": 2.07, "August": 1.42, "September": 4.33, "October": 3.84, "November": 3.88, "December": 5.3}, "wmo_id": 28668}, {"station_id": 28666, "year": 1990, "monthly_data": {"January": 1.0, "February": 6.79, "March": 6.27, "April": 6.19, "May": 3.89, "June": 5.88, "July": 5.74, "August": 5.99, "September": 4.66, "October": 5.51, "November": 7.52, "December": 5.62}, "wmo_id": 28668}, {"station_id": 28666, "year": 1990, "monthly_data": {"January": 2.0, "February": 2.6, "March": 3.34, "April": 4.71, "May": 1.15, "June": 3.86, "July": 3.44, "August": 3.6, "September": 3.08, "October": 3.88, "November": 6.05, "December": 3.89}, "wmo_id": 28668}, {"station_id": 28666, "year": 1991, "monthly_data": {"January": 1.0, "February": 6.64, "March": 5.56, "April": 6.39, "May": 3.87, "June": 3.95, "July": 4.53, "August": 6.07, "September": 7.3, "October": 5.34, "November": 5.69, "December": 5.85}, "wmo_id": 28668}, {"station_id": 28666, "year": 1991, "monthly_data": {"January": 2.0, "February": 4.11, "March": 1.53, "April": 2.35, "May": 0.86, "June": 1.36, "July": 2.19, "August": 4.4, "September": 5.46, "October": 3.55, "November": 2.58, "December": 3.16}, "wmo_id": 28668}, {"station_id": 28666, "year": 1992, "monthly_data": {"January": 1.0, "February": 6.14, "March": 6.44, "April": 4.23, "May": 5.9, "June": 5.33, "July": 5.78, "August": 6.35, "September": 6.65, "October": 5.2, "November": 6.76, "December": 6.5}, "wmo_id": 28668}, {"station_id": 28666, "year": 1992, "monthly_data": {"January": 2.0, "February": 3.4, "March": 3.01, "April": 1.98, "May": 3.59, "June": 3.58, "July": 3.76, "August": 5.03, "September": 5.39, "October": 4.2, "November": 4.68, "December": 4.42}, "wmo_id": 28668}, {"station_id": 28666, "year": 1993, "monthly_data": {"January": 1.0, "February": 6.16, "March": 4.33, "April": 4.91, "May": 5.71, "June": 4.98, "July": 5.24, "August": 5.64, "September": 5.64, "October": 7.48, "November": 7.26, "December": 3.37}, "wmo_id": 28668}, {"station_id": 28666, "year": 1993, "monthly_data": {"January": 2.0, "February": 2.88, "March": 0.83, "April": 2.54, "May": 4.29, "June": 3.75, "July": 3.87, "August": 4.76, "September": 4.41, "October": 6.11, "November": 4.84, "December": 1.14}, "wmo_id": 28668}, {"station_id": 28666, "year": 1994, "monthly_data": {"January": 1.0, "February": 5.31, "March": 3.2, "April": 3.58, "May": 4.94, "June": 5.09, "July": 4.53, "August": 7.29, "September": 6.25, "October": 5.29, "November": 4.35, "December": 6.59}, "wmo_id": 28668}, {"station_id": 28666, "year": 1994, "monthly_data": {"January": 2.0, "February": 1.73, "March": 0.47, "April": 1.27, "May": 2.48, "June": 3.03, "July": 2.74, "August": 5.98, "September": 4.8, "October": 3.2, "November": 2.65, "December": 4.37}, "wmo_id": 28668}, {"station_id": 28666, "year": 1995, "monthly_data": {"January": 1.0, "February": 3.83, "March": 6.31, "April": 4.96, "May": 3.78, "June": 4.65, "July": 5.67, "August": 4.92, "September": 5.16, "October": 4.17, "November": 5.6, "December": 6.59}, "wmo_id": 28668}, {"station_id": 28666, "year": 1995, "monthly_data": {"January": 2.0, "February": 2.14, "March": 3.34, "April": 3.17, "May": 1.98, "June": 3.18, "July": 3.63, "August": 3.51, "September": 3.84, "October": 3.18, "November": 3.95, "December": 4.92}, "wmo_id": 28668}, {"station_id": 28666, "year": 1996, "monthly_data": {"January": 1.0, "February": 5.48, "March": 3.27, "April": 2.1, "May": 5.01, "June": 4.43, "July": 4.8, "August": 5.78, "September": 5.93, "October": 7.95, "November": 5.59, "December": 5.79}, "wmo_id": 28668}, {"station_id": 28666, "year": 1996, "monthly_data": {"January": 2.0, "February": 3.6, "March": 1.85, "April": 0.96, "May": 2.36, "June": 3.11, "July": 2.85, "August": 4.42, "September": 4.67, "October": 7.14, "November": 3.79, "December": 3.85}, "wmo_id": 28668}, {"station_id": 28666, "year": 1997, "monthly_data": {"January": 1.0, "February": 6.37, "March": 5.15, "April": 6.76, "May": 5.22, "June": 4.89, "July": 4.45, "August": 5.4, "September": 5.52, "October": 5.23, "November": 5.47, "December": 6.38}, "wmo_id": 28668}, {"station_id": 28666, "year": 1997, "monthly_data": {"January": 2.0, "February": 1.73, "March": 1.3, "April": 5.05, "May": 2.95, "June": 3.4, "July": 3.21, "August": 3.7, "September": 4.49, "October": 3.18, "November": 3.35, "December": 3.3}, "wmo_id": 28668}, {"station_id": 28666, "year": 1998, "monthly_data": {"January": 1.0, "February": 3.98, "March": 6.32, "April": 2.99, "May": 4.94, "June": 4.47, "July": 5.23, "August": 4.48, "September": 4.78, "October": 6.03, "November": 6.82, "December": 5.21}, "wmo_id": 28668}, {"station_id": 28666, "year": 1998, "monthly_data": {"January": 2.0, "February": 1.35, "March": 1.39, "April": 0.74, "May": 3.2, "June": 2.55, "July": 3.55, "August": 2.47, "September": 3.52, "October": 5.09, "November": 4.86, "December": 2.43}, "wmo_id": 28668}, {"station_id": 28666, "year": 1999, "monthly_data": {"January": 1.0, "February": 6.39, "March": 5.27, "April": 3.92, "May": 5.17, "June": 6.39, "July": 5.49, "August": 5.38, "September": 5.56, "October": 7.33, "November": 5.63, "December": 5.8}, "wmo_id": 28668}, {"station_id": 28666, "year": 1999, "monthly_data": {"January": 2.0, "February": 3.63, "March": 2.38, "April": 0.34, "May": 3.72, "June": 4.57, "July": 4.44, "August": 3.79, "September": 3.6, "October": 5.81, "November": 4.08, "December": 3.75}, "wmo_id": 28668}, {"station_id": 28666, "year": 2000, "monthly_data": {"January": 1.0, "February": 5.79, "March": 5.16, "April": 4.07, "May": 4.78, "June": 6.23, "July": 5.46, "August": 5.08, "September": 5.48, "October": 6.37, "November": 7.82, "December": 4.58}, "wmo_id": 28668}, {"station_id": 28666, "year": 2000, "monthly_data": {"January": 2.0, "February": 1.88, "March": 2.32, "April": 1.86, "May": 2.99, "June": 5.03, "July": 3.85, "August": 3.76, "September": 4.01, "October": 5.19, "November": 5.95, "December": 3.27}, "wmo_id": 28668}, {"station_id": 28666, "year": 2001, "monthly_data": {"January": 1.0, "February": 6.8, "March": 4.42, "April": 6.39, "May": 4.54, "June": 4.52, "July": 5.79, "August": 5.45, "September": 5.94, "October": 6.42, "November": 8.04, "December": 6.84}, "wmo_id": 28668}, {"station_id": 28666, "year": 2001, "monthly_data": {"January": 2.0, "February": 3.57, "March": 1.55, "April": 3.64, "May": 2.54, "June": 2.47, "July": 4.36, "August": 4.23, "September": 4.28, "October": 5.39, "November": 6.35, "December": 4.93}, "wmo_id": 28668}, {"station_id": 28666, "year": 2002, "monthly_data": {"January": 1.0, "February": 7.47, "March": 6.89, "April": 6.06, "May": 4.56, "June": 5.76, "July": 6.99, "August": 5.23, "September": 6.68, "October": 5.73, "November": 6.81, "December": 7.08}, "wmo_id": 28668}, {"station_id": 28666, "year": 2002, "monthly_data": {"January": 2.0, "February": 4.85, "March": 4.73, "April": 4.43, "May": 2.59, "June": 4.73, "July": 5.58, "August": 4.11, "September": 5.66, "October": 3.06, "November": 5.73, "December": 5.73}, "wmo_id": 28668}, {"station_id": 28666, "year": 2003, "monthly_data": {"January": 1.0, "February": 5.33, "March": 4.57, "April": 3.52, "May": 3.82, "June": 6.05, "July": 6.38, "August": 5.81, "September": 4.15, "October": 5.02, "November": 4.99, "December": 5.92}, "wmo_id": 28668}, {"station_id": 28666, "year": 2003, "monthly_data": {"January": 2.0, "February": 2.81, "March": 2.58, "April": 1.36, "May": 2.34, "June": 3.98, "July": 4.94, "August": 4.24, "September": 2.39, "October": 3.54, "November": 3.25, "December": 3.26}, "wmo_id": 28668}, {"station_id": 28666, "year": 2004, "monthly_data": {"January": 1.0, "February": 5.36, "March": 5.11, "April": 4.52, "May": 5.33, "June": 4.83, "July": 5.7, "August": 4.55, "September": 5.33, "October": 6.74, "November": 8.12, "December": 7.2}, "wmo_id": 28668}, {"station_id": 28666, "year": 2004, "monthly_data": {"January": 2.0, "February": 3.56, "March": 2.93, "April": 2.61, "May": 4.22, "June": 2.21, "July": 3.83, "August": 2.91, "September": 4.17, "October": 5.35, "November": 7.38, "December": 6.13}, "wmo_id": 28668}, {"station_id": 28666, "year": 2005, "monthly_data": {"January": 1.0, "February": 5.37, "March": 3.47, "April": 5.85, "May": 5.06, "June": 5.47, "July": 5.44, "August": 5.6, "September": 6.77, "October": 4.84, "November": 5.2, "December": 7.77}, "wmo_id": 28668}, {"station_id": 28666, "year": 2005, "monthly_data": {"January": 2.0, "February": 3.61, "March": 0.94, "April": 3.64, "May": 2.83, "June": 3.9, "July": 4.42, "August": 4.42, "September": 5.71, "October": 3.72, "November": 4.08, "December": 6.89}, "wmo_id": 28668}, {"station_id": 28666, "year": 2006, "monthly_data": {"January": 1.0, "February": 4.88, "March": 4.74, "April": 5.11, "May": 7.89, "June": 5.16, "July": 5.89, "August": 5.74, "September": 5.76, "October": 5.64, "November": 7.21, "December": 6.59}, "wmo_id": 28668}, {"station_id": 28666, "year": 2006, "monthly_data": {"January": 2.0, "February": 0.54, "March": 1.34, "April": 2.46, "May": 6.71, "June": 3.6, "July": 4.59, "August": 5.03, "September": 4.74, "October": 5.02, "November": 6.78, "December": 5.14}, "wmo_id": 28668}, {"station_id": 28666, "year": 2007, "monthly_data": {"January": 1.0, "February": 7.67, "March": 5.53, "April": 5.11, "May": 6.08, "June": 6.49, "July": 6.05, "August": 5.57, "September": 5.46, "October": 6.15, "November": 6.3, "December": 5.47}, "wmo_id": 28668}, {"station_id": 28666, "year": 2007, "monthly_data": {"January": 2.0, "February": 6.0, "March": 3.57, "April": 3.3, "May": 4.94, "June": 5.05, "July": 4.33, "August": 4.42, "September": 4.22, "October": 4.85, "November": 5.12, "December": 3.91}, "wmo_id": 28668}, {"station_id": 28666, "year": 2008, "monthly_data": {"January": 1.0, "February": 4.46, "March": 6.22, "April": 5.72, "May": 4.7, "June": 6.42, "July": 4.53, "August": 5.11, "September": 5.85, "October": 7.12, "November": 5.78, "December": 7.42}, "wmo_id": 28668}, {"station_id": 28666, "year": 2008, "monthly_data": {"January": 2.0, "February": 2.23, "March": 2.96, "April": 3.62, "May": 2.28, "June": 5.39, "July": 3.42, "August": 3.52, "September": 4.46, "October": 6.58, "November": 4.84, "December": 6.37}, "wmo_id": 28668}, {"station_id": 28666, "year": 2009, "monthly_data": {"January": 1.0, "February": 6.03, "March": 5.04, "April": 6.08, "May": 6.45, "June": 5.34, "July": 5.25, "August": 5.78, "September": 6.05, "October": 5.31, "November": 5.9, "December": 8.05}, "wmo_id": 28668}, {"station_id": 28666, "year": 2009, "monthly_data": {"January": 2.0, "February": 2.2, "March": 1.35, "April": 3.91, "May": 5.16, "June": 3.98, "July": 3.98, "August": 4.72, "September": 4.9, "October": 4.55, "November": 4.96, "December": 5.38}, "wmo_id": 28668}, {"station_id": 28666, "year": 2010, "monthly_data": {"January": 1.0, "February": 4.4, "March": 4.03, "April": 5.19, "May": 4.18, "June": 5.12, "July": 5.65, "August": 5.69, "September": 5.21, "October": 6.08, "November": 5.07, "December": 7.69}, "wmo_id": 28668}, {"station_id": 28666, "year": 2010, "monthly_data": {"January": 2.0, "February": 2.52, "March": 1.95, "April": 2.17, "May": 2.19, "June": 3.49, "July": 4.19, "August": 4.56, "September": 3.66, "October": 5.23, "November": 3.42, "December": 6.36}, "wmo_id": 28668}, {"station_id": 28666, "year": 2011, "monthly_data": {"January": 1.0, "February": 4.84, "March": 4.99, "April": 4.33, "May": 6.19, "June": 5.23, "July": 6.83, "August": 5.5, "September": 6.13, "October": 5.85, "November": 6.6, "December": 6.94}, "wmo_id": 28668}, {"station_id": 28666, "year": 2011, "monthly_data": {"January": 2.0, "February": 2.24, "March": 2.94, "April": 1.97, "May": 4.56, "June": 4.07, "July": 5.86, "August": 4.37, "September": 5.07, "October": 4.44, "November": 5.9, "December": 5.86}, "wmo_id": 28668}, {"station_id": 28666, "year": 2012, "monthly_data": {"January": 1.0, "February": 3.19, "March": 3.58, "April": 5.55, "May": 5.58, "June": 5.99, "July": 6.2, "August": 5.23, "September": 5.29, "October": 6.54, "November": 6.26, "December": 8.28}, "wmo_id": 28668}, {"station_id": 28666, "year": 2012, "monthly_data": {"January": 2.0, "February": 1.32, "March": 1.38, "April": 3.15, "May": 2.87, "June": 4.62, "July": 4.74, "August": 3.39, "September": 3.77, "October": 5.48, "November": 5.36, "December": 7.2}, "wmo_id": 28668}, {"station_id": 28666, "year": 2013, "monthly_data": {"January": 1.0, "February": 6.13, "March": 5.76, "April": 6.2, "May": 6.98, "June": 5.47, "July": 4.45, "August": 6.5, "September": 6.76, "October": 6.78, "November": 6.93, "December": 7.46}, "wmo_id": 28668}, {"station_id": 28666, "year": 2013, "monthly_data": {"January": 2.0, "February": 4.05, "March": 3.79, "April": 5.0, "May": 5.32, "June": 4.45, "July": 3.09, "August": 5.17, "September": 5.06, "October": 6.08, "November": 6.17, "December": 6.34}, "wmo_id": 28668}, {"station_id": 28666, "year": 2014, "monthly_data": {"January": 1.0, "February": 6.82, "March": 6.36, "April": 7.72, "May": 6.27, "June": 5.69, "July": 5.28, "August": 7.39, "September": 6.33, "October": 6.4, "November": 8.23, "December": 6.88}, "wmo_id": 28668}, {"station_id": 28666, "year": 2014, "monthly_data": {"January": 2.0, "February": 5.41, "March": 2.42, "April": 5.21, "May": 3.93, "June": 3.48, "July": 3.95, "August": 6.52, "September": 4.28, "October": 5.3, "November": 7.52, "December": 4.92}, "wmo_id": 28668}, {"station_id": 28666, "year": 2015, "monthly_data": {"January": 1.0, "February": 5.83, "March": 5.08, "April": 4.13, "May": 4.72, "June": 6.21, "July": 4.88, "August": 6.84, "September": 6.46, "October": 6.17, "November": 7.2, "December": 6.51}, "wmo_id": 28668}, {"station_id": 28666, "year": 2015, "monthly_data": {"January": 2.0, "February": 3.95, "March": 2.35, "April": 2.55, "May": 3.71, "June": 5.01, "July": 2.88, "August": 5.61, "September": 5.45, "October": 4.82, "November": 6.36, "December": 5.51}, "wmo_id": 28668}, {"station_id": 28666, "year": 2016, "monthly_data": {"January": 1.0, "February": 5.04, "March": 6.35, "April": 6.66, "May": 6.42, "June": 3.41, "July": 6.23, "August": 7.19, "September": 4.36, "October": 6.48, "November": 8.25, "December": 6.75}, "wmo_id": 28668}, {"station_id": 28666, "year": 2016, "monthly_data": {"January": 2.0, "February": 2.94, "March": 5.44, "April": 5.31, "May": 5.15, "June": 2.07, "July": 5.08, "August": 5.23, "September": 2.42, "October": 5.42, "November": 7.93, "December": 6.11}, "wmo_id": 28668}, {"station_id": 28666, "year": 2017, "monthly_data": {"January": 1.0, "February": 6.54, "March": 5.43, "April": 4.21, "May": 5.45, "June": 5.84, "July": 6.19, "August": 6.02, "September": 5.11, "October": 6.18, "November": 6.46, "December": 6.52}, "wmo_id": 28668}, {"station_id": 28666, "year": 2017, "monthly_data": {"January": 2.0, "February": 3.3, "March": 2.44, "April": 2.64, "May": 3.83, "June": 4.82, "July": 4.58, "August": 4.75, "September": 3.74, "October": 4.94, "November": 5.49, "December": 5.64}, "wmo_id": 28668}, {"station_id": 28666, "year": 2018, "monthly_data": {"January": 1.0, "February": 3.3, "March": 4.69, "April": 4.5, "May": 6.57, "June": 6.85, "July": 6.65, "August": 5.51, "September": 6.74, "October": 5.65, "November": 7.45, "December": 7.45}, "wmo_id": 28668}, {"station_id": 28666, "year": 2018, "monthly_data": {"January": 2.0, "February": 2.05, "March": 3.14, "April": 3.24, "May": 5.54, "June": 5.91, "July": 5.66, "August": 4.21, "September": 5.83, "October": 4.56, "November": 6.51, "December": 7.13}, "wmo_id": 28668}, {"station_id": 28666, "year": 2019, "monthly_data": {"January": 1.0, "February": 6.25, "March": 6.06, "April": 5.33, "May": 5.41, "June": 5.7, "July": 6.99, "August": 5.29, "September": 6.81, "October": 6.87, "November": 6.41, "December": 6.9}, "wmo_id": 28668}, {"station_id": 28666, "year": 2019, "monthly_data": {"January": 2.0, "February": 5.11, "March": 5.02, "April": 4.22, "May": 4.19, "June": 3.67, "July": 5.55, "August": 3.23, "September": 5.41, "October": 5.93, "November": 5.61, "December": 6.14}, "wmo_id": 28668}, {"station_id": 28666, "year": 2020, "monthly_data": {"January": 1.0, "February": 7.65, "March": 8.03, "April": 5.78, "May": 5.97, "June": 4.89, "July": 4.71, "August": 5.0, "September": 5.72, "October": 6.31, "November": 6.22, "December": 6.59}, "wmo_id": 28668}, {"station_id": 28666, "year": 2020, "monthly_data": {"January": 2.0, "February": 7.08, "March": 7.55, "April": 4.66, "May": 4.69, "June": 3.84, "July": 3.79, "August": 3.31, "September": 4.72, "October": 5.29, "November": 5.02, "December": 5.88}, "wmo_id": 28668}, {"station_id": 28666, "year": 2021, "monthly_data": {"January": 1.0, "February": 4.6, "March": 5.2, "April": 5.5, "May": 4.8, "June": 4.0, "July": 4.9, "August": 5.7, "September": 4.9, "October": 6.1, "November": 6.5, "December": 5.8}, "wmo_id": 28668}, {"station_id": 28666, "year": 2021, "monthly_data": {"January": 2.0, "February": 1.6, "March": 2.3, "April": 3.6, "May": 3.3, "June": 1.9, "July": 3.8, "August": 4.5, "September": 3.8, "October": 5.3, "November": 5.2, "December": 4.8}, "wmo_id": 28668}, {"station_id": 28666, "year": 2022, "monthly_data": {"January": 1.0, "February": 5.4, "March": 5.6, "April": 5.4, "May": 5.7, "June": 5.3, "July": 6.2, "August": 5.8, "September": 4.7, "October": 6.2, "November": 6.5, "December": 7.1}, "wmo_id": 28668}, {"station_id": 28666, "year": 2022, "monthly_data": {"January": 2.0, "February": 4.4, "March": 3.9, "April": 3.4, "May": 3.9, "June": 3.9, "July": 5.3, "August": 4.7, "September": 3.7, "October": 4.9, "November": 5.2, "December": 6.4}, "wmo_id": 28668}, {"station_id": 28666, "year": 2023, "monthly_data": {"January": 1.0, "February": 5.8, "March": 6.6, "April": 5.1, "May": 3.9, "June": 4.4, "July": 6.0, "August": 5.2, "September": 5.3, "October": 5.8, "November": 6.5, "December": null}, "wmo_id": 28668}, {"station_id": 28666, "year": 2023, "monthly_data": {"January": 2.0, "February": 4.4, "March": 4.7, "April": 3.6, "May": 2.3, "June": 2.4, "July": 4.7, "August": 3.5, "September": 4.0, "October": 4.9, "November": 5.9, "December": null}, "wmo_id": 28668}]